pyheif_pillow_opener/__init__.py
pyheif_pillow_opener-0.2.0.dist-info/LICENSE
pyheif_pillow_opener-0.2.0.dist-info/METADATA
pyheif_pillow_opener-0.2.0.dist-info/WHEEL
pyheif_pillow_opener-0.2.0.dist-info/top_level.txt
pyheif_pillow_opener-0.2.0.dist-info/RECORD
