Metadata-Version: 2.1
Name: pyheif-pillow-opener
Version: 0.2.0
Summary: pyheif-pillow-opener is a simple HEIF/HEIC opener for Pillow base on pyhief library.
Home-page: https://github.com/ciotto/pyheif-pillow-opener
Download-URL: https://github.com/ciotto/pyheif-pillow-opener/archive/v0.2.0.tar.gz
Author: Christian Bianciotto
Author-email: info@ci8.it
License: MIT
Keywords: heif,heic,Pillow
Classifier: Development Status :: 4 - Beta
Classifier: Intended Audience :: Developers
Classifier: License :: OSI Approved :: MIT License
Classifier: Natural Language :: English
Classifier: Operating System :: MacOS :: MacOS X
Classifier: Operating System :: POSIX :: Linux
Classifier: Programming Language :: Python :: 3
Classifier: Programming Language :: Python :: 3.6
Classifier: Programming Language :: Python :: 3.7
Classifier: Programming Language :: Python :: 3.8
Classifier: Programming Language :: Python :: Implementation :: PyPy
Classifier: Topic :: Multimedia :: Graphics
License-File: LICENSE
Requires-Dist: pyheif (==0.7.1)
